MANIFEST.in
README.txt
setup.cfg
setup.py
anthill/__init__.py
anthill.exampletheme.egg-info/PKG-INFO
anthill.exampletheme.egg-info/SOURCES.txt
anthill.exampletheme.egg-info/dependency_links.txt
anthill.exampletheme.egg-info/entry_points.txt
anthill.exampletheme.egg-info/namespace_packages.txt
anthill.exampletheme.egg-info/not-zip-safe
anthill.exampletheme.egg-info/paster_plugins.txt
anthill.exampletheme.egg-info/requires.txt
anthill.exampletheme.egg-info/top_level.txt
anthill/exampletheme/__init__.py
anthill/exampletheme/configure.zcml
anthill/exampletheme/profiles.zcml
anthill/exampletheme/setuphandlers.py
anthill/exampletheme/skins.zcml
anthill/exampletheme/tests.py
anthill/exampletheme/version.txt
anthill/exampletheme/browser/__init__.py
anthill/exampletheme/browser/configure.zcml
anthill/exampletheme/browser/index.html
anthill/exampletheme/browser/interfaces.py
anthill/exampletheme/browser/viewlet.pt
anthill/exampletheme/browser/viewlets.py
anthill/exampletheme/browser/images/README.txt
anthill/exampletheme/browser/images/img01.jpg
anthill/exampletheme/browser/images/img02.jpg
anthill/exampletheme/browser/images/img03.jpg
anthill/exampletheme/browser/images/img04.jpg
anthill/exampletheme/browser/images/spacer.gif
anthill/exampletheme/browser/stylesheets/README.txt
anthill/exampletheme/browser/stylesheets/main.css
anthill/exampletheme/profiles/default/anthill.exampletheme_various.txt
anthill/exampletheme/profiles/default/cssregistry.xml
anthill/exampletheme/profiles/default/import_steps.xml
anthill/exampletheme/profiles/default/jsregistry.xml
anthill/exampletheme/profiles/default/metadata.xml
anthill/exampletheme/profiles/default/skins.xml
anthill/exampletheme/profiles/default/viewlets.xml
anthill/exampletheme/skins/anthill_exampletheme_custom_images/CONTENT.txt
anthill/exampletheme/skins/anthill_exampletheme_custom_templates/CONTENT.txt
anthill/exampletheme/skins/anthill_exampletheme_custom_templates/main_template.pt
anthill/exampletheme/skins/anthill_exampletheme_custom_templates/publicmenu_levels.pt
anthill/exampletheme/skins/anthill_exampletheme_styles/CONTENT.txt
anthill/exampletheme/skins/anthill_exampletheme_styles/base.css.dtml
anthill/exampletheme/skins/anthill_exampletheme_styles/base_properties.props
anthill/exampletheme/skins/anthill_exampletheme_styles/portlets.css.dtml
anthill/exampletheme/skins/anthill_exampletheme_styles/public.css.dtml
