Metadata-Version: 1.0
Name: anthill.exampletheme
Version: 0.2
Summary: Example theme for anthill.skinner
Home-page: UNKNOWN
Author: Simon Pamies
Author-email: s.pamies@banality.de
License: GPL
Keywords: web zope plone anthill skin theme
Platform: UNKNOWN
Classifier: Framework :: Plone
Classifier: Programming Language :: Python
Classifier: Topic :: Software Development :: Libraries :: Python Modules
